COPYING
LICENSE-MPL-FlyingSquirrel
MANIFEST.in
README.md
VERSION
setup.py
flyingsquirrel/__init__.py
flyingsquirrel/api.py
flyingsquirrel/client.py
flyingsquirrel/exceptions.py
flyingsquirrel/utils.py
flyingsquirrel.egg-info/PKG-INFO
flyingsquirrel.egg-info/SOURCES.txt
flyingsquirrel.egg-info/dependency_links.txt
flyingsquirrel.egg-info/top_level.txt
flyingsquirrel.egg-info/zip-safe