Metadata-Version: 1.0
Name: flyingsquirrel
Version: 0.0.1
Summary: Flying Squirrel Client Library
Home-page: UNKNOWN
Author: RabbitMQ Team
Author-email: info@rabbitmq.com
License: MPL v1.1
Platform: any
Classifier: Development Status :: 3 - Alpha
Classifier: Intended Audience :: Developers
Classifier: License :: OSI Approved :: Mozilla Public License 1.1 (MPL 1.1)
Classifier: Operating System :: OS Independent
Classifier: Topic :: Communications
Classifier: Topic :: Internet
Classifier: Topic :: Software Development :: Libraries
